xarm/__init__.py
xarm/build_backend.py
xarm/version.py
xarm/core/__init__.py
xarm/core/version.py
xarm/core/comm/__init__.py
xarm/core/comm/base.py
xarm/core/comm/serial_port.py
xarm/core/comm/socket_port.py
xarm/core/comm/uxbus_cmd_protocol.py
xarm/core/config/__init__.py
xarm/core/config/x_code.py
xarm/core/config/x_config.py
xarm/core/utils/__init__.py
xarm/core/utils/convert.py
xarm/core/utils/crc16.py
xarm/core/utils/debug_print.py
xarm/core/utils/log.py
xarm/core/wrapper/__init__.py
xarm/core/wrapper/uxbus_cmd.py
xarm/core/wrapper/uxbus_cmd_ser.py
xarm/core/wrapper/uxbus_cmd_tcp.py
xarm/tools/__init__.py
xarm/tools/blockly_tool.py
xarm/tools/gcode.py
xarm/tools/list_ports.py
xarm/tools/modbus_tcp.py
xarm/tools/threads.py
xarm/tools/utils.py
xarm/tools/blockly/__init__.py
xarm/tools/blockly/_blockly_base.py
xarm/tools/blockly/_blockly_handler.py
xarm/tools/blockly/_blockly_highlight.py
xarm/tools/blockly/_blockly_node.py
xarm/tools/blockly/_blockly_tool.py
xarm/wrapper/__init__.py
xarm/wrapper/studio_api.py
xarm/wrapper/xarm_api.py
xarm/x3/__init__.py
xarm/x3/base.py
xarm/x3/base_board.py
xarm/x3/code.py
xarm/x3/decorator.py
xarm/x3/events.py
xarm/x3/ft_sensor.py
xarm/x3/gpio.py
xarm/x3/grammar_async.py
xarm/x3/grammar_coroutine.py
xarm/x3/gripper.py
xarm/x3/modbus_tcp.py
xarm/x3/parse.py
xarm/x3/record.py
xarm/x3/report.py
xarm/x3/robotiq.py
xarm/x3/servo.py
xarm/x3/studio.py
xarm/x3/track.py
xarm/x3/utils.py
xarm/x3/xarm.py
xarm_python_sdk-1.16.0.dist-info/METADATA
xarm_python_sdk-1.16.0.dist-info/WHEEL
xarm_python_sdk-1.16.0.dist-info/licenses/LICENSE
xarm_python_sdk-1.16.0.dist-info/RECORD
