Metadata-Version: 2.4
Name: xarm-python-sdk
Version: 1.16.0
Summary: Python SDK for UFACTORY robotic arm 850, xArm 5/6/7, and Lite6.
Project-URL: Homepage, https://www.ufactory.cc
Project-URL: Documentation, https://github.com/xArm-Developer/xArm-Python-SDK/blob/master/doc/api/xarm_api.md
Project-URL: Repository, https://github.com/xArm-Developer/xArm-Python-SDK.git
Project-URL: Issues, https://github.com/xArm-Developer/xArm-Python-SDK/issues
Author-email: Vinman <vinman.wen@ufactory.cc>
Maintainer-email: Vinman <vinman.wen@ufactory.cc>, Minna <minna.zhong@ufactory.cc>
License-File: LICENSE
Classifier: Intended Audience :: Developers
Classifier: Operating System :: OS Independent
Classifier: Programming Language :: Python
Classifier: Programming Language :: Python :: 3
Classifier: Programming Language :: Python :: 3.5
Classifier: Programming Language :: Python :: 3.6
Classifier: Programming Language :: Python :: 3.7
Classifier: Programming Language :: Python :: 3.8
Classifier: Programming Language :: Python :: 3.9
Classifier: Programming Language :: Python :: 3.10
Classifier: Programming Language :: Python :: 3.11
Classifier: Programming Language :: Python :: 3.12
Classifier: Programming Language :: Python :: 3.13
Classifier: Topic :: Software Development
Requires-Python: >=3.5
